shipsim_cli/__init__.py
shipsim_cli/__main__.py
shipsim_cli/shipsim.py
shipsim_cli-0.4.0.dist-info/licenses/LICENSE
shipsim_cli-0.4.0.dist-info/METADATA
shipsim_cli-0.4.0.dist-info/WHEEL
shipsim_cli-0.4.0.dist-info/entry_points.txt
shipsim_cli-0.4.0.dist-info/top_level.txt
shipsim_cli-0.4.0.dist-info/RECORD
