Metadata-Version: 2.4
Name: shipsim-cli
Version: 0.4.0
Summary: Estimate shipping cost using carrier Ship Zones and Rate Cards
Author-email: espehon <espehon@gmail.com>
Project-URL: Homepage, https://github.com/espehon/shipsim-cli
Project-URL: Bug Tracker, https://github.com/espehon/shipsim-cli/issues
Classifier: Programming Language :: Python :: 3
Classifier: Development Status :: 3 - Alpha
Classifier: Environment :: Console
Classifier: License :: OSI Approved :: GNU General Public License v3 (GPLv3)
Classifier: Operating System :: OS Independent
Classifier: Topic :: Utilities
Classifier: Topic :: Scientific/Engineering :: Information Analysis
Requires-Python: >=3.8
License-File: LICENSE
Requires-Dist: pandas>=2.3.0
Requires-Dist: numpy<2.0.0,>=1.26.0
Requires-Dist: openpyxl>=3.1.0
Requires-Dist: questionary>=2.1.0
Requires-Dist: halo>=0.0.31
Requires-Dist: seaborn>=0.13.2
Dynamic: license-file
